sigmaeval/__init__.py
sigmaeval/_evaluators.py
sigmaeval/assertions.py
sigmaeval/core/__init__.py
sigmaeval/core/data_collection.py
sigmaeval/core/exceptions.py
sigmaeval/core/framework.py
sigmaeval/core/models.py
sigmaeval/core/prompts.py
sigmaeval/core/rubric_generator.py
sigmaeval/core/utils.py
sigmaeval/core/writing_styles.py
sigmaeval/metrics.py
sigmaeval_framework-0.1.3.dist-info/LICENSE
sigmaeval_framework-0.1.3.dist-info/METADATA
sigmaeval_framework-0.1.3.dist-info/WHEEL
sigmaeval_framework-0.1.3.dist-info/RECORD
