Metadata-Version: 2.3
Name: sigmaeval-framework
Version: 0.1.3
Summary: The Gen AI App Evaluation Framework
License: Apache-2.0
Author: Itura AI
Requires-Python: >=3.10,<4.0
Classifier: Development Status :: 3 - Alpha
Classifier: Intended Audience :: Developers
Classifier: License :: OSI Approved :: Apache Software License
Classifier: Programming Language :: Python :: 3
Classifier: Programming Language :: Python :: 3.10
Classifier: Programming Language :: Python :: 3.11
Classifier: Programming Language :: Python :: 3.12
Classifier: Programming Language :: Python :: 3.13
Requires-Dist: litellm (>=1.77.5,<2.0.0)
Requires-Dist: numpy (>=1.26.4,<3.0.0)
Requires-Dist: pydantic (>=2.11.9,<3.0.0)
Requires-Dist: scipy (>=1.14.0,<2.0.0)
Requires-Dist: tenacity (>=9.1.2,<10.0.0)
Requires-Dist: tqdm (>=4.66.4,<5.0.0)
Project-URL: Homepage, https://github.com/Itura-AI/sigmaeval
Project-URL: Issues, https://github.com/Itura-AI/sigmaeval/issues
Project-URL: Repository, https://github.com/Itura-AI/sigmaeval
